odoo9_addon_l10n_nl_xaf_auditfile_export-9.0.2.0.0-py3.8-nspkg.pth
odoo_addons/l10n_nl_xaf_auditfile_export/README.rst
odoo_addons/l10n_nl_xaf_auditfile_export/__init__.py
odoo_addons/l10n_nl_xaf_auditfile_export/__openerp__.py
odoo_addons/l10n_nl_xaf_auditfile_export/data/XmlAuditfileFinancieel3.2.xsd
odoo_addons/l10n_nl_xaf_auditfile_export/i18n/l10n_nl_xaf_auditfile_export.pot
odoo_addons/l10n_nl_xaf_auditfile_export/i18n/nl.po
odoo_addons/l10n_nl_xaf_auditfile_export/migrations/9.0.1.0.0/pre-migration.py
odoo_addons/l10n_nl_xaf_auditfile_export/models/__init__.py
odoo_addons/l10n_nl_xaf_auditfile_export/models/ir_qweb.py
odoo_addons/l10n_nl_xaf_auditfile_export/models/xaf_auditfile_export.py
odoo_addons/l10n_nl_xaf_auditfile_export/security/ir.model.access.csv
odoo_addons/l10n_nl_xaf_auditfile_export/static/description/icon.png
odoo_addons/l10n_nl_xaf_auditfile_export/tests/test_l10n_nl_xaf_auditfile_export.py
odoo_addons/l10n_nl_xaf_auditfile_export/views/menu.xml
odoo_addons/l10n_nl_xaf_auditfile_export/views/templates.xml
odoo_addons/l10n_nl_xaf_auditfile_export/views/xaf_auditfile_export.xml
odoo9_addon_l10n_nl_xaf_auditfile_export-9.0.2.0.0.dist-info/METADATA
odoo9_addon_l10n_nl_xaf_auditfile_export-9.0.2.0.0.dist-info/WHEEL
odoo9_addon_l10n_nl_xaf_auditfile_export-9.0.2.0.0.dist-info/namespace_packages.txt
odoo9_addon_l10n_nl_xaf_auditfile_export-9.0.2.0.0.dist-info/top_level.txt
odoo9_addon_l10n_nl_xaf_auditfile_export-9.0.2.0.0.dist-info/RECORD
