Metadata-Version: 2.1
Name: odoo9-addon-l10n-nl-xaf-auditfile-export
Version: 9.0.2.0.0
Summary: Export XAF auditfiles for Dutch tax authorities
Home-page: https://github.com/OCA/l10n-netherlands
Author: Therp BV, Odoo Community Association (OCA)
Author-email: support@odoo-community.org
License: AGPL-3
Platform: UNKNOWN
Classifier: Programming Language :: Python
Classifier: Framework :: Odoo
Classifier: Framework :: Odoo :: 9.0
Classifier: License :: OSI Approved :: GNU Affero General Public License v3
Requires-Python: ~=2.7
Requires-Dist: odoo <9.1a,>=9.0a
